HISTORY.md
MANIFEST.in
README.md
setup.py
jsonpickler/__init__.py
jsonpickler/jsonpickler.py
jsonpickler.egg-info/PKG-INFO
jsonpickler.egg-info/SOURCES.txt
jsonpickler.egg-info/dependency_links.txt
jsonpickler.egg-info/not-zip-safe
jsonpickler.egg-info/top_level.txt