Metadata-Version: 1.0
Name: jsonpickler
Version: 0.1.2
Summary: Python JSON Pickler.
Home-page: UNKNOWN
Author: Martin Skou
Author-email: martinskou@gmail.com
License: MIT license
Platform: UNKNOWN
Classifier: Development Status :: 4 - Beta
Classifier: Intended Audience :: Developers
Classifier: Natural Language :: English
Classifier: License :: OSI Approved :: MIT License
Classifier: Programming Language :: Python
Classifier: Programming Language :: Python :: 2.7
